<annotation>
	<folder>stabbing</folder>
	<filename>stabbing0026.jpg</filename>
	<path>C:/Users/anamu/OneDrive/Desktop/Biomedical Data Science and Informatics/2019 Spring/CPSC 8810 Deep Learning/Project/Labelled Image/stabbing/stabbing0026.jpg</path>
	<source>
		<database>Unknown</database>
	</source>
	<segmented/>
	<size>
		<width>1024</width>
		<height>576</height>
		<depth>3</depth>
	</size>
	<object>
		<name>victim</name>
		<pose>Unspecified</pose>
		<truncated>0</truncated>
		<difficult>0</difficult>
		<bndbox>
			<xmin>701</xmin>
			<ymin>62</ymin>
			<xmax>778</xmax>
			<ymax>160</ymax>
		</bndbox>
	</object>
	<object>
		<name>victim</name>
		<pose>Unspecified</pose>
		<truncated>0</truncated>
		<difficult>0</difficult>
		<bndbox>
			<xmin>469</xmin>
			<ymin>168</ymin>
			<xmax>529</xmax>
			<ymax>264</ymax>
		</bndbox>
	</object>
</annotation>
