<annotation>
	<folder>punching</folder>
	<filename>punching0239.jpg</filename>
	<path>C:/Users/anamu/OneDrive/Desktop/Biomedical Data Science and Informatics/2019 Spring/CPSC 8810 Deep Learning/Project/Labelled Image/punching/punching0239.jpg</path>
	<source>
		<database>Unknown</database>
	</source>
	<segmented/>
	<size>
		<width>430</width>
		<height>400</height>
		<depth>3</depth>
	</size>
	<object>
		<name>victim</name>
		<pose>Unspecified</pose>
		<truncated>0</truncated>
		<difficult>0</difficult>
		<bndbox>
			<xmin>22</xmin>
			<ymin>133</ymin>
			<xmax>92</xmax>
			<ymax>219</ymax>
		</bndbox>
	</object>
	<object>
		<name>victim</name>
		<pose>Unspecified</pose>
		<truncated>0</truncated>
		<difficult>0</difficult>
		<bndbox>
			<xmin>247</xmin>
			<ymin>85</ymin>
			<xmax>343</xmax>
			<ymax>219</ymax>
		</bndbox>
	</object>
</annotation>
