<annotation>
	<folder>slapping</folder>
	<filename>slapping0048.jpg</filename>
	<path>C:/Users/anamu/OneDrive/Desktop/Biomedical Data Science and Informatics/2019 Spring/CPSC 8810 Deep Learning/Project/Labelled Image/slapping/slapping0048.jpg</path>
	<source>
		<database>Unknown</database>
	</source>
	<segmented/>
	<size>
		<width>634</width>
		<height>446</height>
		<depth>3</depth>
	</size>
	<object>
		<name>victim</name>
		<pose>Unspecified</pose>
		<truncated>0</truncated>
		<difficult>0</difficult>
		<bndbox>
			<xmin>456</xmin>
			<ymin>109</ymin>
			<xmax>481</xmax>
			<ymax>141</ymax>
		</bndbox>
	</object>
	<object>
		<name>victim</name>
		<pose>Unspecified</pose>
		<truncated>0</truncated>
		<difficult>0</difficult>
		<bndbox>
			<xmin>390</xmin>
			<ymin>105</ymin>
			<xmax>405</xmax>
			<ymax>125</ymax>
		</bndbox>
	</object>
	<object>
		<name>victim</name>
		<pose>Unspecified</pose>
		<truncated>0</truncated>
		<difficult>0</difficult>
		<bndbox>
			<xmin>314</xmin>
			<ymin>113</ymin>
			<xmax>326</xmax>
			<ymax>127</ymax>
		</bndbox>
	</object>
	<object>
		<name>victim</name>
		<pose>Unspecified</pose>
		<truncated>0</truncated>
		<difficult>0</difficult>
		<bndbox>
			<xmin>72</xmin>
			<ymin>114</ymin>
			<xmax>106</xmax>
			<ymax>155</ymax>
		</bndbox>
	</object>
	<object>
		<name>victim</name>
		<pose>Unspecified</pose>
		<truncated>0</truncated>
		<difficult>0</difficult>
		<bndbox>
			<xmin>334</xmin>
			<ymin>119</ymin>
			<xmax>353</xmax>
			<ymax>141</ymax>
		</bndbox>
	</object>
	<object>
		<name>victim</name>
		<pose>Unspecified</pose>
		<truncated>0</truncated>
		<difficult>0</difficult>
		<bndbox>
			<xmin>4</xmin>
			<ymin>167</ymin>
			<xmax>30</xmax>
			<ymax>209</ymax>
		</bndbox>
	</object>
	<object>
		<name>victim</name>
		<pose>Unspecified</pose>
		<truncated>0</truncated>
		<difficult>0</difficult>
		<bndbox>
			<xmin>422</xmin>
			<ymin>121</ymin>
			<xmax>433</xmax>
			<ymax>136</ymax>
		</bndbox>
	</object>
	<object>
		<name>victim</name>
		<pose>Unspecified</pose>
		<truncated>0</truncated>
		<difficult>0</difficult>
		<bndbox>
			<xmin>376</xmin>
			<ymin>302</ymin>
			<xmax>417</xmax>
			<ymax>350</ymax>
		</bndbox>
	</object>
</annotation>
